{
  "weapons": [
    {
      "id": "jassm_er",
      "name": "AGM-158B JASSM-ER",
      "full_name": "Joint Air-to-Surface Standoff Missile Extended Range",
      "domain": "AIR",
      "type": "CRUISE_MISSILE",
      "country": "USA",
      "range_km": 925,
      "speed_mach": 0.85,
      "speed_kmh": 1045,
      "warhead_kg": 450,
      "warhead_type": "UNITARY_PENETRATOR",
      "cep_m": 3,
      "guidance": ["INS", "GPS", "IIR_TERMINAL"],
      "launch_platform": ["F-35A", "F-35C", "B-1B", "B-2A", "B-52H", "F-15E", "F-16C", "F/A-18E"],
      "cruise_altitude_m": [30, 1000],
      "max_g_load": 4.0,
      "fuel_type": "JP-10",
      "stealth": true,
      "detection_radius_km": 50,
      "evasion_capable": true,
      "quantity_limit": 50,
      "unit_cost_musd": 1.5
    },
    {
      "id": "lrasm",
      "name": "AGM-158C LRASM",
      "full_name": "Long Range Anti-Ship Missile",
      "domain": "AIR",
      "type": "ANTI_SHIP_MISSILE",
      "country": "USA",
      "range_km": 370,
      "speed_mach": 0.85,
      "speed_kmh": 1045,
      "warhead_kg": 450,
      "warhead_type": "BLAST_FRAGMENTATION",
      "cep_m": 5,
      "guidance": ["INS", "GPS", "MULTI_SPECTRAL_SEEKER"],
      "launch_platform": ["F/A-18E", "F/A-18F", "B-1B", "MK41_VLS"],
      "cruise_altitude_m": [5, 30],
      "max_g_load": 5.0,
      "fuel_type": "JP-10",
      "stealth": true,
      "detection_radius_km": 40,
      "evasion_capable": true,
      "quantity_limit": 60,
      "unit_cost_musd": 3.0
    },
    {
      "id": "tomahawk_block5",
      "name": "BGM-109 Tomahawk Block V",
      "full_name": "Tomahawk Land Attack Missile Block V",
      "domain": "SEA",
      "type": "CRUISE_MISSILE",
      "country": "USA",
      "range_km": 1600,
      "speed_mach": 0.74,
      "speed_kmh": 890,
      "warhead_kg": 454,
      "warhead_type": "UNITARY",
      "cep_m": 5,
      "guidance": ["TERCOM", "GPS", "DSMAC_IV"],
      "launch_platform": ["MK41_VLS", "MK45_VLS", "TORPEDO_TUBE_21IN"],
      "cruise_altitude_m": [15, 100],
      "max_g_load": 3.5,
      "fuel_type": "F-44",
      "stealth": false,
      "detection_radius_km": 30,
      "evasion_capable": true,
      "quantity_limit": 100,
      "unit_cost_musd": 2.0
    },
    {
      "id": "atacms_m39a1",
      "name": "MGM-140B ATACMS M39A1",
      "full_name": "Army Tactical Missile System",
      "domain": "LAND",
      "type": "BALLISTIC_MISSILE",
      "country": "USA",
      "range_km": 300,
      "speed_mach": 3.0,
      "speed_kmh": 3675,
      "warhead_kg": 230,
      "warhead_type": "UNITARY_BLAST_FRAGMENTATION",
      "cep_m": 9,
      "guidance": ["GPS", "INS"],
      "launch_platform": ["M270_MLRS", "M142_HIMARS"],
      "cruise_altitude_m": [50000, 150000],
      "max_g_load": null,
      "fuel_type": "SOLID_PROPELLANT",
      "stealth": false,
      "detection_radius_km": 20,
      "evasion_capable": false,
      "quantity_limit": 50,
      "unit_cost_musd": 1.7
    },
    {
      "id": "storm_shadow",
      "name": "Storm Shadow / SCALP-EG",
      "full_name": "Storm Shadow (UK) / SCALP Emploi General (France)",
      "domain": "AIR",
      "type": "CRUISE_MISSILE",
      "country": "UK_FR",
      "range_km": 560,
      "speed_mach": 0.8,
      "speed_kmh": 1000,
      "warhead_kg": 450,
      "warhead_type": "BROACH_PENETRATOR",
      "cep_m": 10,
      "guidance": ["INS", "GPS", "TERPROM_TERRAIN", "IIR_TERMINAL"],
      "launch_platform": ["Tornado_GR4", "Typhoon_FGR4", "Rafale", "F-16"],
      "cruise_altitude_m": [30, 1000],
      "max_g_load": 3.0,
      "fuel_type": "KEROSENE",
      "stealth": true,
      "detection_radius_km": 45,
      "evasion_capable": true,
      "quantity_limit": 40,
      "unit_cost_musd": 1.2
    },
    {
      "id": "brahmos_a",
      "name": "BrahMos-A",
      "full_name": "BrahMos Air-Launched Supersonic Cruise Missile",
      "domain": "AIR",
      "type": "CRUISE_MISSILE",
      "country": "IN_RU",
      "range_km": 500,
      "speed_mach": 2.8,
      "speed_kmh": 3430,
      "warhead_kg": 300,
      "warhead_type": "SEMI_ARMOUR_PIERCING",
      "cep_m": 3,
      "guidance": ["INS", "GPS", "ACTIVE_RADAR_SEEKER"],
      "launch_platform": ["Su-30MKI"],
      "cruise_altitude_m": [10, 15000],
      "max_g_load": 5.0,
      "fuel_type": "KEROSENE",
      "stealth": false,
      "detection_radius_km": 60,
      "evasion_capable": true,
      "quantity_limit": 30,
      "unit_cost_musd": 3.0
    },
    {
      "id": "kh101",
      "name": "Kh-101",
      "full_name": "Kh-101 Subsonic Strategic Cruise Missile",
      "domain": "AIR",
      "type": "CRUISE_MISSILE",
      "country": "RU",
      "range_km": 5500,
      "speed_mach": 0.77,
      "speed_kmh": 940,
      "warhead_kg": 400,
      "warhead_type": "THERMOBARIC_OR_NUCLEAR",
      "cep_m": 10,
      "guidance": ["INS", "GLONASS", "OPTICAL_CORRELATION"],
      "launch_platform": ["Tu-95MS", "Tu-160", "Tu-22M3"],
      "cruise_altitude_m": [30, 6000],
      "max_g_load": 3.0,
      "fuel_type": "KEROSENE",
      "stealth": true,
      "detection_radius_km": 45,
      "evasion_capable": true,
      "quantity_limit": 20,
      "unit_cost_musd": 13.0
    },
    {
      "id": "kinzhal",
      "name": "Kh-47M2 Kinzhal",
      "full_name": "Kh-47M2 Kinzhal Hypersonic Aeroballistic Missile",
      "domain": "AIR",
      "type": "HYPERSONIC_BALLISTIC",
      "country": "RU",
      "range_km": 2000,
      "speed_mach": 10.0,
      "speed_kmh": 12250,
      "warhead_kg": 500,
      "warhead_type": "CONVENTIONAL_OR_NUCLEAR",
      "cep_m": 1,
      "guidance": ["INS", "GLONASS", "ACTIVE_RADAR_TERMINAL"],
      "launch_platform": ["MiG-31K", "Tu-22M3", "Su-34"],
      "cruise_altitude_m": [20000, 40000],
      "max_g_load": null,
      "fuel_type": "SOLID_PROPELLANT",
      "stealth": false,
      "detection_radius_km": 70,
      "evasion_capable": true,
      "quantity_limit": 10,
      "unit_cost_musd": 12.0,
      "tot_tolerance_s": 0.5
    },
    {
      "id": "df26",
      "name": "DF-26",
      "full_name": "Dong Feng 26 Intermediate Range Ballistic Missile",
      "domain": "LAND",
      "type": "IRBM",
      "country": "CN",
      "range_km": 4000,
      "speed_mach": 18.0,
      "speed_kmh": 22050,
      "warhead_kg": 1200,
      "warhead_type": "CONVENTIONAL_OR_NUCLEAR",
      "cep_m": 150,
      "guidance": ["INS", "BEIDOU", "MaRV_TERMINAL"],
      "launch_platform": ["TEL_8x8"],
      "cruise_altitude_m": [800000, 1200000],
      "max_g_load": null,
      "fuel_type": "SOLID_PROPELLANT",
      "stealth": false,
      "detection_radius_km": 100,
      "evasion_capable": false,
      "quantity_limit": 15,
      "unit_cost_musd": 10.0
    },
    {
      "id": "iskander_m",
      "name": "9K720 Iskander-M",
      "full_name": "Iskander-M Short Range Ballistic Missile",
      "domain": "LAND",
      "type": "SRBM",
      "country": "RU",
      "range_km": 500,
      "speed_mach": 6.0,
      "speed_kmh": 7350,
      "warhead_kg": 480,
      "warhead_type": "CLUSTER_OR_PENETRATOR",
      "cep_m": 5,
      "guidance": ["INS", "GLONASS", "OPTICAL_CORRELATOR", "ACTIVE_RADAR"],
      "launch_platform": ["SPU_9P78-1"],
      "cruise_altitude_m": [50000, 100000],
      "max_g_load": 20.0,
      "fuel_type": "SOLID_PROPELLANT",
      "stealth": false,
      "detection_radius_km": 50,
      "evasion_capable": true,
      "quantity_limit": 40,
      "unit_cost_musd": 3.0
    },
    {
      "id": "harpoon_agm84",
      "name": "AGM-84 Harpoon",
      "full_name": "AGM/RGM/UGM-84 Harpoon Block II+",
      "domain": "AIR",
      "type": "ANTI_SHIP_MISSILE",
      "country": "USA",
      "range_km": 280,
      "speed_mach": 0.85,
      "speed_kmh": 1040,
      "warhead_kg": 221,
      "warhead_type": "BLAST_FRAGMENTATION",
      "cep_m": 5,
      "guidance": ["INS", "GPS", "ACTIVE_RADAR_SEEKER"],
      "launch_platform": ["F/A-18", "P-8A", "B-52H", "DDG", "FFG", "SSN"],
      "cruise_altitude_m": [2, 15],
      "max_g_load": 5.0,
      "fuel_type": "JP-10",
      "stealth": false,
      "detection_radius_km": 35,
      "evasion_capable": true,
      "quantity_limit": 60,
      "unit_cost_musd": 1.4
    },
    {
      "id": "scalp_naval",
      "name": "MdCN / Naval Cruise Missile",
      "full_name": "Missile de Croisière Naval (France)",
      "domain": "SEA",
      "type": "CRUISE_MISSILE",
      "country": "FR",
      "range_km": 1400,
      "speed_mach": 0.8,
      "speed_kmh": 980,
      "warhead_kg": 450,
      "warhead_type": "PENETRATOR",
      "cep_m": 10,
      "guidance": ["INS", "GPS", "TERRAIN_FOLLOWING", "IIR_TERMINAL"],
      "launch_platform": ["SYLVER_A70_VLS"],
      "cruise_altitude_m": [15, 1000],
      "max_g_load": 3.0,
      "fuel_type": "KEROSENE",
      "stealth": true,
      "detection_radius_km": 40,
      "evasion_capable": true,
      "quantity_limit": 30,
      "unit_cost_musd": 1.8
    },
    {
      "id": "yj18",
      "name": "YJ-18",
      "full_name": "YJ-18 Anti-Ship/Land Attack Cruise Missile",
      "domain": "SEA",
      "type": "CRUISE_MISSILE",
      "country": "CN",
      "range_km": 540,
      "speed_mach": 2.5,
      "speed_kmh": 3062,
      "warhead_kg": 300,
      "warhead_type": "SEMI_ARMOUR_PIERCING",
      "cep_m": 5,
      "guidance": ["INS", "BEIDOU", "ACTIVE_RADAR_TERMINAL"],
      "launch_platform": ["TYPE_055_VLS", "TYPE_052D_VLS", "SSN"],
      "cruise_altitude_m": [5, 20],
      "max_g_load": 5.0,
      "fuel_type": "KEROSENE",
      "stealth": false,
      "detection_radius_km": 55,
      "evasion_capable": true,
      "quantity_limit": 40,
      "unit_cost_musd": 2.5
    },
    {
      "id": "taurus_kepd350",
      "name": "TAURUS KEPD 350",
      "full_name": "TAURUS Kinetic Energy Penetration and Destroy 350",
      "domain": "AIR",
      "type": "CRUISE_MISSILE",
      "country": "DE_SE",
      "range_km": 500,
      "speed_mach": 0.95,
      "speed_kmh": 1165,
      "warhead_kg": 481,
      "warhead_type": "MEPHISTO_TANDEM_PENETRATOR",
      "cep_m": 3,
      "guidance": ["INS", "GPS_GALILEO", "TERCOM", "IIR_TERMINAL"],
      "launch_platform": ["Tornado_IDS", "Eurofighter_Typhoon", "F-15K"],
      "cruise_altitude_m": [30, 1500],
      "max_g_load": 4.0,
      "fuel_type": "KEROSENE",
      "stealth": true,
      "detection_radius_km": 45,
      "evasion_capable": true,
      "quantity_limit": 35,
      "unit_cost_musd": 1.0
    },
    {
      "id": "p800_oniks",
      "name": "P-800 Oniks / Yakhont",
      "full_name": "P-800 Oniks Supersonic Anti-Ship Missile",
      "domain": "SEA",
      "type": "ANTI_SHIP_MISSILE",
      "country": "RU",
      "range_km": 600,
      "speed_mach": 2.5,
      "speed_kmh": 3062,
      "warhead_kg": 250,
      "warhead_type": "SEMI_ARMOUR_PIERCING",
      "cep_m": 5,
      "guidance": ["INS", "GLONASS", "ACTIVE_RADAR_SEEKER"],
      "launch_platform": ["BASTION_P_COASTAL", "Type_949A_SSN", "MiG-29K"],
      "cruise_altitude_m": [10, 14000],
      "max_g_load": 5.0,
      "fuel_type": "KEROSENE",
      "stealth": false,
      "detection_radius_km": 60,
      "evasion_capable": true,
      "quantity_limit": 30,
      "unit_cost_musd": 1.2
    }
  ],
  "platforms": [
    {
      "id": "b2_spirit",
      "name": "B-2A Spirit",
      "full_name": "Northrop Grumman B-2A Spirit Strategic Bomber",
      "domain": "AIR",
      "type": "PLATFORM_BOMBER",
      "country": "USA",
      "range_km": 11100,
      "speed_mach": 0.95,
      "speed_kmh": 1010,
      "payload_kg": 18000,
      "compatible_weapons": ["jassm_er", "lrasm", "storm_shadow"],
      "crew": 2,
      "stealth": true,
      "base_requirement": "HEAVY_BOMBER_RUNWAY",
      "refuelable": true,
      "icon": "bomber"
    },
    {
      "id": "b52h",
      "name": "B-52H Stratofortress",
      "full_name": "Boeing B-52H Stratofortress Strategic Bomber",
      "domain": "AIR",
      "type": "PLATFORM_BOMBER",
      "country": "USA",
      "range_km": 14162,
      "speed_mach": 0.86,
      "speed_kmh": 1047,
      "payload_kg": 31500,
      "compatible_weapons": ["jassm_er", "lrasm", "harpoon_agm84", "tomahawk_block5"],
      "crew": 5,
      "stealth": false,
      "base_requirement": "HEAVY_BOMBER_RUNWAY",
      "refuelable": true,
      "icon": "bomber"
    },
    {
      "id": "f35a",
      "name": "F-35A Lightning II",
      "full_name": "Lockheed Martin F-35A Lightning II CTOL",
      "domain": "AIR",
      "type": "PLATFORM_FIGHTER",
      "country": "USA",
      "range_km": 2220,
      "speed_mach": 1.6,
      "speed_kmh": 1960,
      "payload_kg": 8160,
      "compatible_weapons": ["jassm_er", "lrasm"],
      "crew": 1,
      "stealth": true,
      "base_requirement": "STANDARD_RUNWAY",
      "refuelable": true,
      "icon": "fighter"
    },
    {
      "id": "f16c",
      "name": "F-16C/D Block 50/52",
      "full_name": "Lockheed Martin F-16C/D Fighting Falcon",
      "domain": "AIR",
      "type": "PLATFORM_FIGHTER",
      "country": "USA",
      "range_km": 1600,
      "speed_mach": 2.0,
      "speed_kmh": 2450,
      "payload_kg": 7700,
      "compatible_weapons": ["jassm_er", "harpoon_agm84", "storm_shadow"],
      "crew": 1,
      "stealth": false,
      "base_requirement": "STANDARD_RUNWAY",
      "refuelable": true,
      "icon": "fighter"
    },
    {
      "id": "rafale",
      "name": "Dassault Rafale F3-R",
      "full_name": "Dassault Rafale Multi-Role Fighter",
      "domain": "AIR",
      "type": "PLATFORM_FIGHTER",
      "country": "FR",
      "range_km": 3700,
      "speed_mach": 1.8,
      "speed_kmh": 2205,
      "payload_kg": 9500,
      "compatible_weapons": ["storm_shadow", "scalp_naval", "harpoon_agm84"],
      "crew": 1,
      "stealth": false,
      "base_requirement": "STANDARD_RUNWAY",
      "refuelable": true,
      "icon": "fighter"
    },
    {
      "id": "su30mki",
      "name": "Su-30MKI",
      "full_name": "Sukhoi Su-30MKI Air Superiority Fighter",
      "domain": "AIR",
      "type": "PLATFORM_FIGHTER",
      "country": "IN",
      "range_km": 3000,
      "speed_mach": 2.0,
      "speed_kmh": 2120,
      "payload_kg": 8000,
      "compatible_weapons": ["brahmos_a"],
      "crew": 2,
      "stealth": false,
      "base_requirement": "STANDARD_RUNWAY",
      "refuelable": true,
      "icon": "fighter"
    },
    {
      "id": "kc135r",
      "name": "KC-135R Stratotanker",
      "full_name": "Boeing KC-135R Stratotanker Aerial Refueling Aircraft",
      "domain": "AIR",
      "type": "PLATFORM_TANKER",
      "country": "USA",
      "range_km": 14800,
      "speed_mach": 0.85,
      "speed_kmh": 1040,
      "fuel_transfer_kg": 68000,
      "crew": 3,
      "stealth": false,
      "base_requirement": "HEAVY_RUNWAY",
      "icon": "tanker"
    },
    {
      "id": "kc46a",
      "name": "KC-46A Pegasus",
      "full_name": "Boeing KC-46A Pegasus Aerial Refueling Aircraft",
      "domain": "AIR",
      "type": "PLATFORM_TANKER",
      "country": "USA",
      "range_km": 12900,
      "speed_mach": 0.86,
      "speed_kmh": 1055,
      "fuel_transfer_kg": 96700,
      "crew": 3,
      "stealth": false,
      "base_requirement": "HEAVY_RUNWAY",
      "icon": "tanker"
    },
    {
      "id": "ea18g_growler",
      "name": "EA-18G Growler",
      "full_name": "Boeing EA-18G Growler Electronic Warfare Aircraft",
      "domain": "AIR",
      "type": "PLATFORM_EW",
      "country": "USA",
      "range_km": 1850,
      "speed_mach": 1.8,
      "speed_kmh": 1900,
      "ew_systems": ["AN_ALQ-99", "AN_ALQ-218", "ICAP_III"],
      "jam_radius_km": 200,
      "jam_types": ["RADAR", "COMMS", "GPS"],
      "crew": 2,
      "stealth": false,
      "base_requirement": "STANDARD_RUNWAY",
      "icon": "ew_aircraft"
    },
    {
      "id": "arleigh_burke_ddg",
      "name": "DDG Arleigh Burke-class",
      "full_name": "Arleigh Burke-class Guided-Missile Destroyer",
      "domain": "SEA",
      "type": "PLATFORM_DESTROYER",
      "country": "USA",
      "range_km": 8300,
      "speed_knots": 31,
      "vls_cells": 90,
      "compatible_weapons": ["tomahawk_block5", "lrasm", "harpoon_agm84"],
      "crew": 281,
      "icon": "destroyer"
    },
    {
      "id": "type055",
      "name": "Type 055 Renhai-class",
      "full_name": "Type 055 Renhai-class Guided-Missile Cruiser",
      "domain": "SEA",
      "type": "PLATFORM_CRUISER",
      "country": "CN",
      "range_km": 9000,
      "speed_knots": 32,
      "vls_cells": 112,
      "compatible_weapons": ["yj18", "yj18"],
      "crew": 300,
      "icon": "cruiser"
    },
    {
      "id": "ohio_ssgn",
      "name": "Ohio-class SSGN",
      "full_name": "Ohio-class Guided-Missile Submarine",
      "domain": "SEA",
      "type": "PLATFORM_SUBMARINE",
      "country": "USA",
      "range_km": 18500,
      "speed_knots": 25,
      "vls_cells": 154,
      "compatible_weapons": ["tomahawk_block5"],
      "crew": 155,
      "icon": "submarine"
    },
    {
      "id": "m142_himars",
      "name": "M142 HIMARS",
      "full_name": "High Mobility Artillery Rocket System",
      "domain": "LAND",
      "type": "PLATFORM_MLRS",
      "country": "USA",
      "range_km": 300,
      "speed_kmh": 85,
      "rockets_per_salvo": 6,
      "compatible_weapons": ["atacms_m39a1"],
      "crew": 3,
      "icon": "mlrs"
    },
    {
      "id": "bastion_p",
      "name": "K-300P Bastion-P",
      "full_name": "K-300P Bastion-P Coastal Defense Missile System",
      "domain": "LAND",
      "type": "PLATFORM_COASTAL",
      "country": "RU",
      "range_km": 0,
      "compatible_weapons": ["p800_oniks"],
      "missiles_per_system": 36,
      "crew": 100,
      "icon": "coastal_battery"
    }
  ],
  "threats": [
    {
      "id": "s400",
      "name": "S-400 Triumf",
      "full_name": "S-400 Triumf / SA-21 Growler SAM System",
      "country": "RU",
      "type": "SAM",
      "engagement_range_km": 400,
      "engagement_altitude_m": [10, 30000],
      "p_kill_base": 0.85,
      "missiles_per_battery": 32,
      "reload_time_s": 300,
      "radar_types": ["91N6E_ACQUISITION", "92N6E_ENGAGEMENT"],
      "radar_range_km": 600,
      "effective_against": ["AIRCRAFT", "CRUISE_MISSILE", "BALLISTIC_MISSILE"]
    },
    {
      "id": "s300v4",
      "name": "S-300V4",
      "full_name": "S-300V4 / SA-23 Anti-Ballistic Missile System",
      "country": "RU",
      "type": "SAM",
      "engagement_range_km": 400,
      "engagement_altitude_m": [25, 30000],
      "p_kill_base": 0.80,
      "missiles_per_battery": 48,
      "reload_time_s": 240,
      "effective_against": ["AIRCRAFT", "BALLISTIC_MISSILE", "IRBM"]
    },
    {
      "id": "patriot_pac3",
      "name": "Patriot PAC-3 MSE",
      "full_name": "Patriot Advanced Capability-3 Missile Segment Enhancement",
      "country": "USA",
      "type": "SAM",
      "engagement_range_km": 100,
      "engagement_altitude_m": [60, 24000],
      "p_kill_base": 0.90,
      "missiles_per_battery": 32,
      "reload_time_s": 200,
      "effective_against": ["AIRCRAFT", "CRUISE_MISSILE", "BALLISTIC_MISSILE", "HYPERSONIC"]
    },
    {
      "id": "thaad",
      "name": "THAAD",
      "full_name": "Terminal High Altitude Area Defense",
      "country": "USA",
      "type": "SAM",
      "engagement_range_km": 200,
      "engagement_altitude_m": [40000, 150000],
      "p_kill_base": 0.95,
      "missiles_per_battery": 48,
      "reload_time_s": 600,
      "effective_against": ["IRBM", "SRBM", "BALLISTIC_MISSILE", "HYPERSONIC"]
    },
    {
      "id": "hq9b",
      "name": "HQ-9B",
      "full_name": "HQ-9B Chinese Long-Range SAM System",
      "country": "CN",
      "type": "SAM",
      "engagement_range_km": 300,
      "engagement_altitude_m": [500, 30000],
      "p_kill_base": 0.80,
      "missiles_per_battery": 32,
      "reload_time_s": 270,
      "effective_against": ["AIRCRAFT", "CRUISE_MISSILE", "BALLISTIC_MISSILE"]
    },
    {
      "id": "f22_raptor_cap",
      "name": "F-22A Raptor CAP",
      "full_name": "F-22A Raptor Combat Air Patrol Interceptor",
      "country": "USA",
      "type": "INTERCEPTOR_AIRCRAFT",
      "engagement_range_km": 160,
      "p_kill_base": 0.75,
      "missiles_per_aircraft": 6,
      "aircraft_per_flight": 2,
      "speed_mach": 2.25,
      "stealth": true,
      "effective_against": ["AIRCRAFT", "CRUISE_MISSILE"]
    }
  ]
}
